plk_package/__init__.py
plk_package/sum.py
plk_package/product/__init__.py
plk_package/product/product.py
plk_package-0.0.1.dist-info/METADATA
plk_package-0.0.1.dist-info/WHEEL
plk_package-0.0.1.dist-info/top_level.txt
plk_package-0.0.1.dist-info/RECORD
