Metadata-Version: 2.1
Name: plk-package
Version: 0.0.1
Summary: My first Python package
Home-page: UNKNOWN
Author: Philip Luke K 
Author-email: philip_luke@ce.iitr.ac.in
License: UNKNOWN
Keywords: python,first package
Platform: UNKNOWN
Classifier: Development Status :: 3 - Alpha
Classifier: Intended Audience :: Education
Classifier: Programming Language :: Python :: 2
Classifier: Programming Language :: Python :: 3
Classifier: Operating System :: OS Independent
